Metadata-Version: 1.0
Name: scikitcrf-ner
Version: 3.2
Summary: Enity Recognition using ScikitCRF
Home-page: https://github.com/manikandan-velu/scikitcrf_NER
Author: Manikandan Thangavelu
Author-email: tmanikandan05@gmail.com
License: MIT
Keywords: scikitCRF entity entityrecognition crf ner
Platform: UNKNOWN
